ChangeLog.rst
LICENSE
MANIFEST.in
README.rst
setup.py
django_seven/__init__.py
django_seven.egg-info/PKG-INFO
django_seven.egg-info/SOURCES.txt
django_seven.egg-info/dependency_links.txt
django_seven.egg-info/top_level.txt
django_seven/compat/__init__.py
django_seven/compat/__init__.pyc
django_seven/compat/decorators.py
django_seven/compat/decorators.pyc
django_seven/compat/auth/__init__.py
django_seven/compat/auth/permissions.py
django_seven/compat/auth/reset_password.py
django_seven/compat/auth/urls.py
django_seven/compat/db/__init__.py
django_seven/compat/db/__init__.pyc
django_seven/compat/db/meta.py
django_seven/compat/db/transaction.py
django_seven/compat/db/transaction.pyc
django_seven/compat/forms/__init__.py
django_seven/compat/forms/constants.py
django_seven/compat/forms/utils.py
django_seven/compat/test/__init__.py
django_seven/compat/test/client.py
django_seven/compat/test/sessions.py
django_seven/deprecated_rules/__init__.py
django_seven/deprecated_rules/__init__.pyc
django_seven/deprecated_rules/helpers.py
django_seven/deprecated_rules/helpers.pyc
django_seven/deprecated_rules/new_helpers.py
django_seven/deprecated_rules/new_helpers.pyc
django_seven/deprecated_rules/rules.py
django_seven/deprecated_rules/rules.pyc
django_seven/deprecated_rules/management/__init__.py
django_seven/deprecated_rules/management/__init__.pyc
django_seven/deprecated_rules/management/commands/__init__.py
django_seven/deprecated_rules/management/commands/check_deprecated_rules.py
django_seven/tools/__init__.py
django_seven/tools/migration_helpers.py
django_seven/tools/management/__init__.py
django_seven/tools/management/commands/__init__.py
django_seven/tools/management/commands/diff_migrations.py